dev/__init__.py
dev/tlsabara/__init__.py
dev/tlsabara/imp_prod.py
dev/tlsabara/queries.py
dev/tlsabara/runner.py
dev/tlsabara/testing.py
glpipci/__init__.py
glpipci/commons/__init__.py
glpipci/commons/webs.py
glpipci/comunicator/__init__.py
glpipci/comunicator/v10_0/__init__.py
glpipci/comunicator/v10_0/api.py
glpipci/comunicator/v10_0/interface_errors.py
glpipci/comunicator/v10_0/patterns.py
glpipci/comunicator/v10_0/endpoints/__init__.py
glpipci/comunicator/v10_0/endpoints/commons.py
glpipci/comunicator/v10_0/endpoints/tickets/__init__.py
glpipci/comunicator/v10_0/endpoints/tickets/core.py
glpipci/comunicator/v10_0/endpoints/tickets/itil_folowups.py
glpipci/comunicator/v10_0/endpoints/tickets/itil_solutions.py
glpipci/comunicator/v10_0/endpoints/tickets/ticket_user.py
glpipci-0.1.3.dist-info/licenses/LICENSE.txt
glpipci-0.1.3.dist-info/METADATA
glpipci-0.1.3.dist-info/WHEEL
glpipci-0.1.3.dist-info/top_level.txt
glpipci-0.1.3.dist-info/RECORD
