Metadata-Version: 2.4
Name: glpipci
Version: 0.1.3
Summary: Um cliente Python para a API do GLPI
Home-page: https://github.com/tlsabara/glpipci
Author: Thiago Sabará
Author-email: Thiago Sabará <thi.sil.sab@gmail.com>
License: MIT
Project-URL: Homepage, https://github.com/tlsabara/glpipci
Classifier: Programming Language :: Python :: 3.10
Classifier: License :: OSI Approved :: MIT License
Classifier: Operating System :: OS Independent
Requires-Python: >=3.10
License-File: LICENSE.txt
Requires-Dist: anyio==4.9.0
Requires-Dist: backports.tarfile==1.2.0
Requires-Dist: build==1.2.2.post1
Requires-Dist: certifi==2025.4.26
Requires-Dist: cffi==1.17.1
Requires-Dist: charset-normalizer==3.4.2
Requires-Dist: cryptography==45.0.2
Requires-Dist: docutils==0.21.2
Requires-Dist: exceptiongroup==1.3.0
Requires-Dist: h11==0.16.0
Requires-Dist: httpcore==1.0.9
Requires-Dist: httpx==0.28.1
Requires-Dist: id==1.5.0
Requires-Dist: idna==3.10
Requires-Dist: importlib_metadata==8.7.0
Requires-Dist: jaraco.classes==3.4.0
Requires-Dist: jaraco.context==6.0.1
Requires-Dist: jaraco.functools==4.1.0
Requires-Dist: jeepney==0.9.0
Requires-Dist: keyring==25.6.0
Requires-Dist: markdown-it-py==3.0.0
Requires-Dist: mdurl==0.1.2
Requires-Dist: more-itertools==10.7.0
Requires-Dist: nh3==0.2.21
Requires-Dist: packaging==25.0
Requires-Dist: pycparser==2.22
Requires-Dist: Pygments==2.19.1
Requires-Dist: pyproject_hooks==1.2.0
Requires-Dist: python-dotenv==1.1.0
Requires-Dist: readme_renderer==44.0
Requires-Dist: requests==2.32.3
Requires-Dist: requests-toolbelt==1.0.0
Requires-Dist: rfc3986==2.0.0
Requires-Dist: rich==14.0.0
Requires-Dist: SecretStorage==3.3.3
Requires-Dist: sniffio==1.3.1
Requires-Dist: tomli==2.2.1
Requires-Dist: twine==6.1.0
Requires-Dist: typing_extensions==4.13.2
Requires-Dist: urllib3==2.4.0
Requires-Dist: zipp==3.21.0
Dynamic: license-file
